Cryptem.py
cryptem.py
Cryptem-0.1.3.dist-info/METADATA
Cryptem-0.1.3.dist-info/WHEEL
Cryptem-0.1.3.dist-info/top_level.txt
Cryptem-0.1.3.dist-info/RECORD
