Metadata-Version: 2.1
Name: Cryptem
Version: 0.1.3
Summary: Cryptographic applications library based on elliptic curve cryptography
Home-page: https://ipfs.io/ipns/k2k4r8ld8q6344t8dop0rwuk8f3vhpo42un6zrnrffogaayr7xv59p83
Author: emendir
Project-URL: Source Code on IPFS, https://ipfs.io/ipns/k2k4r8ld8q6344t8dop0rwuk8f3vhpo42un6zrnrffogaayr7xv59p83
Project-URL: Github, https://github.com/emendir/Cryptem-Python
Classifier: Programming Language :: Python :: 3
Classifier: Operating System :: OS Independent
Requires-Python: >=3.6
Requires-Dist: eciespy
Requires-Dist: coincurve
Requires-Dist: cryptography
